{
  "url": "http://127.0.0.1:4000/graphql",
  "connections": 10,
  "sampleInt": 1000,
  "pipelining": 1,
  "duration": 10,
  "samples": 10,
  "start": "2023-03-01T11:50:41.301Z",
  "finish": "2023-03-01T11:50:51.305Z",
  "errors": 0,
  "timeouts": 0,
  "mismatches": 0,
  "non2xx": 0,
  "resets": 0,
  "1xx": 0,
  "2xx": 5810,
  "3xx": 0,
  "4xx": 0,
  "5xx": 0,
  "statusCodeStats": {
    "200": {
      "count": 5810
    }
  },
  "latency": {
    "average": 16.72,
    "mean": 16.72,
    "stddev": 2.62,
    "min": 14,
    "max": 51,
    "p0_001": 14,
    "p0_01": 14,
    "p0_1": 14,
    "p1": 14,
    "p2_5": 15,
    "p10": 15,
    "p25": 15,
    "p50": 16,
    "p75": 17,
    "p90": 19,
    "p97_5": 22,
    "p99": 28,
    "p99_9": 46,
    "p99_99": 51,
    "p99_999": 51,
    "totalCount": 5810
  },
  "requests": {
    "average": 581,
    "mean": 581,
    "stddev": 20.33,
    "min": 549,
    "max": 620,
    "total": 5810,
    "p0_001": 549,
    "p0_01": 549,
    "p0_1": 549,
    "p1": 549,
    "p2_5": 549,
    "p10": 549,
    "p25": 569,
    "p50": 580,
    "p75": 586,
    "p90": 607,
    "p97_5": 620,
    "p99": 620,
    "p99_9": 620,
    "p99_99": 620,
    "p99_999": 620,
    "sent": 5820
  },
  "throughput": {
    "average": 467148.8,
    "mean": 467148.8,
    "stddev": 16356,
    "min": 441396,
    "max": 498480,
    "total": 4671240,
    "p0_001": 441599,
    "p0_01": 441599,
    "p0_1": 441599,
    "p1": 441599,
    "p2_5": 441599,
    "p10": 441599,
    "p25": 457727,
    "p50": 466431,
    "p75": 471295,
    "p90": 488191,
    "p97_5": 498687,
    "p99": 498687,
    "p99_9": 498687,
    "p99_99": 498687,
    "p99_999": 498687
  }
}