{
  "url": "http://127.0.0.1:4000/graphql",
  "connections": 10,
  "sampleInt": 1000,
  "pipelining": 1,
  "duration": 10.01,
  "samples": 10,
  "start": "2023-02-20T16:23:18.677Z",
  "finish": "2023-02-20T16:23:28.683Z",
  "errors": 0,
  "timeouts": 0,
  "mismatches": 0,
  "non2xx": 0,
  "resets": 0,
  "1xx": 0,
  "2xx": 3909,
  "3xx": 0,
  "4xx": 0,
  "5xx": 0,
  "statusCodeStats": {
    "200": {
      "count": 3909
    }
  },
  "latency": {
    "average": 25.07,
    "mean": 25.07,
    "stddev": 2.89,
    "min": 21,
    "max": 58,
    "p0_001": 21,
    "p0_01": 21,
    "p0_1": 22,
    "p1": 22,
    "p2_5": 22,
    "p10": 22,
    "p25": 23,
    "p50": 24,
    "p75": 26,
    "p90": 29,
    "p97_5": 30,
    "p99": 35,
    "p99_9": 48,
    "p99_99": 58,
    "p99_999": 58,
    "totalCount": 3909
  },
  "requests": {
    "average": 390.9,
    "mean": 390.9,
    "stddev": 20.27,
    "min": 339,
    "max": 416,
    "total": 3909,
    "p0_001": 339,
    "p0_01": 339,
    "p0_1": 339,
    "p1": 339,
    "p2_5": 339,
    "p10": 339,
    "p25": 383,
    "p50": 391,
    "p75": 400,
    "p90": 411,
    "p97_5": 416,
    "p99": 416,
    "p99_9": 416,
    "p99_99": 416,
    "p99_999": 416,
    "sent": 3919
  },
  "throughput": {
    "average": 432716.8,
    "mean": 432716.8,
    "stddev": 22446.64,
    "min": 375273,
    "max": 460512,
    "total": 4327263,
    "p0_001": 375295,
    "p0_01": 375295,
    "p0_1": 375295,
    "p1": 375295,
    "p2_5": 375295,
    "p10": 375295,
    "p25": 424191,
    "p50": 432895,
    "p75": 442879,
    "p90": 455167,
    "p97_5": 460543,
    "p99": 460543,
    "p99_9": 460543,
    "p99_99": 460543,
    "p99_999": 460543
  }
}