{
  "url": "http://127.0.0.1:4000/graphql",
  "connections": 10,
  "sampleInt": 1000,
  "pipelining": 1,
  "duration": 11,
  "samples": 11,
  "start": "2023-03-01T11:54:24.582Z",
  "finish": "2023-03-01T11:54:35.583Z",
  "errors": 0,
  "timeouts": 0,
  "mismatches": 0,
  "non2xx": 0,
  "resets": 0,
  "1xx": 0,
  "2xx": 14488,
  "3xx": 0,
  "4xx": 0,
  "5xx": 0,
  "statusCodeStats": {
    "200": {
      "count": 14488
    }
  },
  "latency": {
    "average": 7.09,
    "mean": 7.09,
    "stddev": 1.86,
    "min": 3,
    "max": 36,
    "p0_001": 3,
    "p0_01": 3,
    "p0_1": 4,
    "p1": 4,
    "p2_5": 5,
    "p10": 5,
    "p25": 6,
    "p50": 7,
    "p75": 8,
    "p90": 9,
    "p97_5": 11,
    "p99": 12,
    "p99_9": 18,
    "p99_99": 36,
    "p99_999": 36,
    "totalCount": 14488
  },
  "requests": {
    "average": 1317.1,
    "mean": 1317.1,
    "stddev": 40.81,
    "min": 1236,
    "max": 1383,
    "total": 14488,
    "p0_001": 1236,
    "p0_01": 1236,
    "p0_1": 1236,
    "p1": 1236,
    "p2_5": 1236,
    "p10": 1273,
    "p25": 1292,
    "p50": 1316,
    "p75": 1359,
    "p90": 1369,
    "p97_5": 1383,
    "p99": 1383,
    "p99_9": 1383,
    "p99_99": 1383,
    "p99_999": 1383,
    "sent": 14498
  },
  "throughput": {
    "average": 831045.82,
    "mean": 831045.82,
    "stddev": 25733.03,
    "min": 779916,
    "max": 872673,
    "total": 9141928,
    "p0_001": 780287,
    "p0_01": 780287,
    "p0_1": 780287,
    "p1": 780287,
    "p2_5": 780287,
    "p10": 803327,
    "p25": 815615,
    "p50": 830463,
    "p75": 857599,
    "p90": 864255,
    "p97_5": 872959,
    "p99": 872959,
    "p99_9": 872959,
    "p99_99": 872959,
    "p99_999": 872959
  }
}